LICENSE
MANIFEST.in
README.rst
requirements.txt
setup.cfg
setup.py
Cantiz_PyChromecast.egg-info/PKG-INFO
Cantiz_PyChromecast.egg-info/SOURCES.txt
Cantiz_PyChromecast.egg-info/dependency_links.txt
Cantiz_PyChromecast.egg-info/not-zip-safe
Cantiz_PyChromecast.egg-info/requires.txt
Cantiz_PyChromecast.egg-info/top_level.txt
pychromecast/__init__.py
pychromecast/authority_keys_pb2.py
pychromecast/cast_channel_pb2.py
pychromecast/config.py
pychromecast/dial.py
pychromecast/discovery.py
pychromecast/error.py
pychromecast/logging_pb2.py
pychromecast/socket_client.py
pychromecast/controllers/__init__.py
pychromecast/controllers/dashcast.py
pychromecast/controllers/media.py
pychromecast/controllers/multizone.py
pychromecast/controllers/plex.py
pychromecast/controllers/spotify.py
pychromecast/controllers/youtube.py