Metadata-Version: 1.1
Name: Cantiz-PyChromecast
Version: 3.2.2
Summary: Python module to talk to Google Chromecast.
Home-page: https://github.com/karthikpanicker/pychromecast
Author: Karthik Raveendran
Author-email: karthik@attinadsoftware.com
License: MIT
Platform: any
Classifier: Intended Audience :: Developers
Classifier: License :: OSI Approved :: MIT License
Classifier: Operating System :: OS Independent
Classifier: Programming Language :: Python
Classifier: Programming Language :: Python :: 2
Classifier: Programming Language :: Python :: 3
Classifier: Topic :: Software Development :: Libraries :: Python Modules
